db_verifier/__init__.py
db_verifier/data_structures.py
db_verifier/run.py
db_verifier.sql
db_verifier-0.1.0.dist-info/LICENSE
db_verifier-0.1.0.dist-info/METADATA
db_verifier-0.1.0.dist-info/WHEEL
db_verifier-0.1.0.dist-info/entry_points.txt
db_verifier-0.1.0.dist-info/RECORD
