Metadata-Version: 2.1
Name: db-verifier
Version: 0.1.0
Summary: Linter for PostgreSQL DB structure: analysis, verification, optimization.
Author: Vasily Nikonov
Requires-Python: >=3.8,<4.0
Classifier: Programming Language :: Python :: 3
Classifier: Programming Language :: Python :: 3.8
Classifier: Programming Language :: Python :: 3.9
Classifier: Programming Language :: Python :: 3.10
Classifier: Programming Language :: Python :: 3.11
Classifier: Programming Language :: Python :: 3.12
Requires-Dist: argparse (>=1.4.0,<2.0.0)
Requires-Dist: psycopg (>=3.1.18,<4.0.0)
Requires-Dist: pydantic (>=2.6.3,<3.0.0)
Requires-Dist: tabulate (>=0.9.0,<0.10.0)
